CONTRIBUTING.md
COPYING
MANIFEST.in
README.rst
extras_require.json
pyproject.toml
setup.py
diffoscope/__init__.py
diffoscope/changes.py
diffoscope/config.py
diffoscope/diff.py
diffoscope/difference.py
diffoscope/environ.py
diffoscope/exc.py
diffoscope/excludes.py
diffoscope/external_tools.py
diffoscope/feeders.py
diffoscope/logging.py
diffoscope/main.py
diffoscope/path.py
diffoscope/profiling.py
diffoscope/progress.py
diffoscope/tempfiles.py
diffoscope/tools.py
diffoscope/utils.py
diffoscope.egg-info/PKG-INFO
diffoscope.egg-info/SOURCES.txt
diffoscope.egg-info/dependency_links.txt
diffoscope.egg-info/entry_points.txt
diffoscope.egg-info/requires.txt
diffoscope.egg-info/top_level.txt
diffoscope/comparators/__init__.py
diffoscope/comparators/android.py
diffoscope/comparators/apk.py
diffoscope/comparators/ar.py
diffoscope/comparators/arsc.py
diffoscope/comparators/asar.py
diffoscope/comparators/berkeley_db.py
diffoscope/comparators/binary.py
diffoscope/comparators/binwalk.py
diffoscope/comparators/bzip2.py
diffoscope/comparators/cbfs.py
diffoscope/comparators/cpio.py
diffoscope/comparators/deb.py
diffoscope/comparators/debian.py
diffoscope/comparators/debian_fallback.py
diffoscope/comparators/decompile.py
diffoscope/comparators/device.py
diffoscope/comparators/dex.py
diffoscope/comparators/directory.py
diffoscope/comparators/docx.py
diffoscope/comparators/dtb.py
diffoscope/comparators/elf.py
diffoscope/comparators/ffprobe.py
diffoscope/comparators/fit.py
diffoscope/comparators/fontconfig.py
diffoscope/comparators/fonts.py
diffoscope/comparators/fsimage.py
diffoscope/comparators/gettext.py
diffoscope/comparators/gif.py
diffoscope/comparators/git.py
diffoscope/comparators/gnumeric.py
diffoscope/comparators/gzip.py
diffoscope/comparators/haskell.py
diffoscope/comparators/hdf.py
diffoscope/comparators/html.py
diffoscope/comparators/icc.py
diffoscope/comparators/image.py
diffoscope/comparators/ipk.py
diffoscope/comparators/iso9660.py
diffoscope/comparators/java.py
diffoscope/comparators/javascript.py
diffoscope/comparators/json.py
diffoscope/comparators/kbx.py
diffoscope/comparators/llvm.py
diffoscope/comparators/lz4.py
diffoscope/comparators/lzip.py
