Metadata-Version: 2.4
Name: diffoscope
Version: 303
Summary: in-depth comparison of files, archives, and directories
Home-page: https://diffoscope.org/
Author: Diffoscope developers
Author-email: diffoscope@lists.reproducible-builds.org
License: GPL-3+
Project-URL: Issues, https://salsa.debian.org/reproducible-builds/diffoscope/-/issues
Project-URL: Merge requests, https://salsa.debian.org/reproducible-builds/diffoscope/-/merge_requests
Classifier: Development Status :: 5 - Production/Stable
Classifier: Intended Audience :: Developers
Classifier: License :: OSI Approved :: GNU General Public License v3 or later (GPLv3+)
Classifier: Operating System :: POSIX
Classifier: Programming Language :: Python
Classifier: Programming Language :: Python :: 3
Classifier: Programming Language :: Python :: 3.7
Classifier: Programming Language :: Python :: 3.8
Classifier: Programming Language :: Python :: 3.9
Classifier: Programming Language :: Python :: 3.10
Classifier: Topic :: Utilities
Requires-Python: >=3.7
License-File: COPYING
Requires-Dist: python-magic
Requires-Dist: libarchive-c
Provides-Extra: distro-detection
Requires-Dist: distro; extra == "distro-detection"
Provides-Extra: cmdline
Requires-Dist: argcomplete; extra == "cmdline"
Requires-Dist: progressbar; extra == "cmdline"
Provides-Extra: comparators
Requires-Dist: androguard; extra == "comparators"
Requires-Dist: binwalk; extra == "comparators"
Requires-Dist: defusedxml; extra == "comparators"
Requires-Dist: guestfs; extra == "comparators"
Requires-Dist: jsondiff; extra == "comparators"
Requires-Dist: pypdf; extra == "comparators"
Requires-Dist: python-debian; extra == "comparators"
Requires-Dist: pyxattr; extra == "comparators"
Requires-Dist: rpm-python; extra == "comparators"
Requires-Dist: tlsh; extra == "comparators"
Dynamic: author
Dynamic: author-email
Dynamic: classifier
Dynamic: description
Dynamic: description-content-type
Dynamic: home-page
Dynamic: license
Dynamic: license-file
Dynamic: project-url
Dynamic: provides-extra
Dynamic: requires-dist
Dynamic: requires-python
Dynamic: summary
